compas_invocations/__init__.py
compas_invocations/build.py
compas_invocations/console.py
compas_invocations/docs.py
compas_invocations/style.py
compas_invocations/tests.py
compas_invocations-1.0.2.dist-info/AUTHORS.md
compas_invocations-1.0.2.dist-info/LICENSE
compas_invocations-1.0.2.dist-info/METADATA
compas_invocations-1.0.2.dist-info/WHEEL
compas_invocations-1.0.2.dist-info/top_level.txt
compas_invocations-1.0.2.dist-info/RECORD
